checkengine/_constraints/_Constraint.py
checkengine/_constraints/_NotNull.py
checkengine/_constraints/_Numbers.py
checkengine/_constraints/_OneOf.py
checkengine/_constraints/_StatColumn.py
checkengine/_constraints/_TextLength.py
checkengine/_constraints/_TextRegex.py
checkengine/_constraints/_Unique.py
checkengine/validate_df.py
checkengine-0.2.0.dist-info/LICENSE
checkengine-0.2.0.dist-info/WHEEL
checkengine-0.2.0.dist-info/METADATA
checkengine-0.2.0.dist-info/RECORD
