Metadata-Version: 2.1
Name: checkengine
Version: 0.2.0
Summary: Data-quality checks for PySpark
Home-page: https://github.com/mikulskibartosz/check-engine
License: MIT
Author: Bartosz Mikulski
Author-email: mail@mikulskibartosz.name
Requires-Python: >=3.8,<4.0
Classifier: License :: OSI Approved :: MIT License
Classifier: Programming Language :: Python :: 3
Classifier: Programming Language :: Python :: 3.8
Requires-Dist: pyspark (==3.0.3)
Project-URL: Repository, https://github.com/mikulskibartosz/check-engine
